LICENSE
MANIFEST.in
README.rst
osrm.py
setup.py
test.py
osrm_py.egg-info/PKG-INFO
osrm_py.egg-info/SOURCES.txt
osrm_py.egg-info/dependency_links.txt
osrm_py.egg-info/requires.txt
osrm_py.egg-info/top_level.txt