Metadata-Version: 1.1
Name: osrm-py
Version: 0.1
Summary: Python client for OSRM API
Home-page: https://github.com/gojuno/osrm-py
Author: Alexander Verbitsky
Author-email: habibutsu@gmail.com
License: BSD
Keywords: osrm
Platform: UNKNOWN
Classifier: Development Status :: 5 - Production/Stable
Classifier: Topic :: Utilities
Classifier: Programming Language :: Python
Classifier: License :: OSI Approved :: BSD License
